XGeoML/__init__.py
XGeoML/fast_train.py
XGeoML/fasttrain.py
XGeoML/preprocess.py
XGeoML/train_model.py
XGeoML/w_matrix.py
XGeoML-0.1.6.dist-info/METADATA
XGeoML-0.1.6.dist-info/WHEEL
XGeoML-0.1.6.dist-info/top_level.txt
XGeoML-0.1.6.dist-info/RECORD
