Metadata-Version: 2.1
Name: XGeoML
Version: 0.1.6
Summary: A ensemble framework for explainable geospatial machine Learning models
Home-page: https://github.com/UrbanGISer/XGeoML
Author: Lingbo Liu
Author-email: lingboliu@fas.harvard.edu
License: MIT
Platform: UNKNOWN
Requires-Dist: scikit-learn
Requires-Dist: numpy
Requires-Dist: scipy
Requires-Dist: joblib
Requires-Dist: pandas
Requires-Dist: lime
Requires-Dist: shap
Requires-Dist: tqdm
